_dynet.cpython-314-darwin.so
libdynet.dylib
dynet_viz.py
dynet.py
dynet_config.py
dynet38.dylibs/libdynet.dylib
dynet38-2.2.dist-info/RECORD
dynet38-2.2.dist-info/WHEEL
dynet38-2.2.dist-info/top_level.txt
dynet38-2.2.dist-info/METADATA
